{"kind":"identitytoolkit#DownloadAccountResponse","users":[{"localId":"2BHTmhtuKGHIXi6UuYF106kMWGea","lastLoginAt":"1750239312790","emailVerified":false,"email":"max@gmail.com","salt":"fakeSalthaRlYxK5eW7GkcPkZlnk","passwordHash":"fakeHash:salt=fakeSalthaRlYxK5eW7GkcPkZlnk:password=234567","passwordUpdatedAt":1750239290546,"validSince":"1750239290","createdAt":"1750239290546","providerUserInfo":[{"providerId":"password","email":"max@gmail.com","federatedId":"max@gmail.com","rawId":"max@gmail.com"}],"lastRefreshAt":"2025-06-18T09:35:12.790Z"}]}