{"kind":"identitytoolkit#DownloadAccountResponse","users":[{"localId":"DmS3yFSoP8FN1fxTiZ657GAcsXQy","lastLoginAt":"1750239150043","emailVerified":false,"email":"max@gmail.com","salt":"fakeSaltfk9il1nu9cbFj7704rkz","passwordHash":"fakeHash:salt=fakeSaltfk9il1nu9cbFj7704rkz:password=234567","passwordUpdatedAt":1750238352044,"validSince":"1750238352","createdAt":"1750238352044","providerUserInfo":[{"providerId":"password","email":"max@gmail.com","federatedId":"max@gmail.com","rawId":"max@gmail.com"}],"lastRefreshAt":"2025-06-18T09:32:30.043Z"}]}